{"nodes": [{"id": "d_projects_anch_framework_src_core_anch_core_mergeresult_cs", "label": "MergeResult.cs", "file_type": "code", "source_file": "src/Core/Anch.Core/MergeResult.cs", "source_location": "L1"}, {"id": "csharp_namespace:12657cbd5c8d81ab", "label": "Anch.Core", "file_type": "code", "source_file": "src/Core/Anch.Core/MergeResult.cs", "source_location": "L1", "type": "namespace", "metadata": {"kind": "csharp_namespace", "namespace": "Anch.Core"}}, {"id": "d_projects_anch_framework_src_core_anch_core_mergeresult_anch_core_mergeresult", "label": "MergeResult", "file_type": "code", "source_file": "src/Core/Anch.Core/MergeResult.cs", "source_location": "L3", "metadata": {"namespace": "Anch.Core", "scope_chain": ["s3"]}, "_callable": true}], "edges": [{"source": "d_projects_anch_framework_src_core_anch_core_mergeresult_cs", "target": "csharp_namespace:12657cbd5c8d81ab", "relation": "contains", "confidence": "EXTRACTED", "source_file": "src/Core/Anch.Core/MergeResult.cs", "source_location": "L1", "weight": 1.0}, {"source": "d_projects_anch_framework_src_core_anch_core_mergeresult_cs", "target": "d_projects_anch_framework_src_core_anch_core_mergeresult_anch_core_mergeresult", "relation": "contains", "confidence": "EXTRACTED", "source_file": "src/Core/Anch.Core/MergeResult.cs", "source_location": "L3", "weight": 1.0}, {"source": "d_projects_anch_framework_src_core_anch_core_mergeresult_anch_core_mergeresult", "target": "d_projects_anch_framework_src_core_anch_core_mergeresult_anch_core_mergeresult", "relation": "references", "confidence": "EXTRACTED", "source_file": "src/Core/Anch.Core/MergeResult.cs", "source_location": "L18", "weight": 1.0, "context": "field", "metadata": {"ref_token": "MergeResult"}}], "raw_calls": [], "csharp_type_table": {"path": "D:\\Projects\\Anch.Framework\\src\\Core\\Anch.Core\\MergeResult.cs", "table": {"Empty": "MergeResult", "removingItems": "IEnumerable", "combineItems": "IEnumerable", "addingItems": "IEnumerable", "RemovingItems": "IReadOnlyList", "CombineItems": "IReadOnlyList", "AddingItems": "IReadOnlyList"}}}